i3cols/__init__.py
i3cols/cli.py
i3cols/cols.py
i3cols/dtypes.py
i3cols/enums.py
i3cols/extract.py
i3cols/i3_to_numpy_converter.py
i3cols/operators.py
i3cols/phys.py
i3cols/pulses.py
i3cols/regexes.py
i3cols/utils.py
i3cols-0.1.4.dist-info/LICENSE
i3cols-0.1.4.dist-info/METADATA
i3cols-0.1.4.dist-info/WHEEL
i3cols-0.1.4.dist-info/entry_points.txt
i3cols-0.1.4.dist-info/top_level.txt
i3cols-0.1.4.dist-info/RECORD
