Metadata-Version: 2.1
Name: i3cols
Version: 0.1.4
Summary: Numpy columnar storage for IceCube data
Home-page: https://github.com/jllanfranchi/i3cols
Author: Justin L. Lanfranchi
Author-email: jll1062@phys.psu.edu
License: MIT
Platform: UNKNOWN
Classifier: License :: OSI Approved :: MIT License
Requires-Python: >=2.7
Requires-Dist: numba (>=0.45)
